{
  "metadata": {
    "scaling_rule": "Enoki_Scaled",
    "optimizer": "dana-mk4",
    "target_omega": 4.0
  },
  "average_curvature": {
    "kappa_mean": 0.009311664757409074,
    "kappa_std": 0.002718720229777253
  },
  "curvature_by_size": [
    {
      "size": 6,
      "non_emb_params": 7077888,
      "L_star": 3.8144834706265307,
      "lr_star": 0.00079011506779831,
      "kappa": 0.013503263247080599,
      "n_points": 9
    },
    {
      "size": 8,
      "non_emb_params": 18874368,
      "L_star": 3.575793147527005,
      "lr_star": 0.0005224573501143054,
      "kappa": 0.010689679548363036,
      "n_points": 9
    },
    {
      "size": 10,
      "non_emb_params": 34406400,
      "L_star": 3.429683870104298,
      "lr_star": 0.0003635564835191308,
      "kappa": 0.009165763696659623,
      "n_points": 9
    },
    {
      "size": 12,
      "non_emb_params": 63700992,
      "L_star": 3.2774038014326545,
      "lr_star": 0.0002423847713604392,
      "kappa": 0.008024719043475608,
      "n_points": 9
    },
    {
      "size": 14,
      "non_emb_params": 96337920,
      "L_star": 3.1791831543134386,
      "lr_star": 0.00016070436111999034,
      "kappa": 0.006947079540183735,
      "n_points": 9
    },
    {
      "size": 16,
      "non_emb_params": 150994944,
      "L_star": 3.0698913662660665,
      "lr_star": 0.00010765253188950777,
      "kappa": 0.0061163250939987555,
      "n_points": 9
    },
    {
      "size": 18,
      "non_emb_params": 207028224,
      "L_star": 2.988350672099248,
      "lr_star": 7.537001536216726e-05,
      "kappa": 0.005354501962733586,
      "n_points": 5
    },
    {
      "size": 20,
      "non_emb_params": 294912000,
      "L_star": 2.9039983861938574,
      "lr_star": 5.4795766542161526e-05,
      "kappa": 0.011260865688088968,
      "n_points": 8
    },
    {
      "size": 22,
      "non_emb_params": 380633088,
      "L_star": 2.8468804438117097,
      "lr_star": 4.0019583723882474e-05,
      "kappa": 0.013437845576197458,
      "n_points": 8
    },
    {
      "size": 24,
      "non_emb_params": 509607936,
      "L_star": 2.782220335310655,
      "lr_star": 4.302582782893669e-05,
      "kappa": 0.008616604177309374,
      "n_points": 8
    }
  ],
  "loss_sensitivity": {
    "lr_errors": [
      0.1,
      0.2,
      0.3,
      0.5
    ],
    "extrapolation_sizes": [
      8,
      12,
      16,
      20,
      24,
      28,
      32,
      36,
      40
    ],
    "delta_losses": {
      "8": {
        "error_10pct": 8.458744549190782e-05,
        "error_20pct": 0.00030953044561905806,
        "error_30pct": 0.00064096851126803,
        "error_50pct": 0.0015308558801161798
      },
      "12": {
        "error_10pct": 8.458744549190782e-05,
        "error_20pct": 0.00030953044561905806,
        "error_30pct": 0.00064096851126803,
        "error_50pct": 0.0015308558801161798
      },
      "16": {
        "error_10pct": 8.458744549190782e-05,
        "error_20pct": 0.00030953044561905806,
        "error_30pct": 0.00064096851126803,
        "error_50pct": 0.0015308558801161798
      },
      "20": {
        "error_10pct": 8.458744549190782e-05,
        "error_20pct": 0.00030953044561905806,
        "error_30pct": 0.00064096851126803,
        "error_50pct": 0.0015308558801161798
      },
      "24": {
        "error_10pct": 8.458744549190782e-05,
        "error_20pct": 0.00030953044561905806,
        "error_30pct": 0.00064096851126803,
        "error_50pct": 0.0015308558801161798
      },
      "28": {
        "error_10pct": 8.458744549190782e-05,
        "error_20pct": 0.00030953044561905806,
        "error_30pct": 0.00064096851126803,
        "error_50pct": 0.0015308558801161798
      },
      "32": {
        "error_10pct": 8.458744549190782e-05,
        "error_20pct": 0.00030953044561905806,
        "error_30pct": 0.00064096851126803,
        "error_50pct": 0.0015308558801161798
      },
      "36": {
        "error_10pct": 8.458744549190782e-05,
        "error_20pct": 0.00030953044561905806,
        "error_30pct": 0.00064096851126803,
        "error_50pct": 0.0015308558801161798
      },
      "40": {
        "error_10pct": 8.458744549190782e-05,
        "error_20pct": 0.00030953044561905806,
        "error_30pct": 0.00064096851126803,
        "error_50pct": 0.0015308558801161798
      }
    }
  }
}